nominal_streaming-0.7.11.dist-info/METADATA
nominal_streaming-0.7.11.dist-info/WHEEL
nominal_streaming.libs/libgcc_s-0bf60adc.so.1
nominal_streaming/__init__.py
nominal_streaming/_nominal_streaming.abi3.so
nominal_streaming/_nominal_streaming.pyi
nominal_streaming/nominal_dataset_stream.py
nominal_streaming/py.typed
nominal_streaming-0.7.11.dist-info/RECORD
