Metadata-Version: 2.4
Name: nominal-streaming
Version: 0.7.11
Classifier: Programming Language :: Python :: 3
Classifier: Programming Language :: Rust
Classifier: License :: OSI Approved :: MIT License
Classifier: Operating System :: OS Independent
Requires-Dist: typing-extensions>=4,<5
Requires-Dist: python-dateutil>=0.0.0
Summary: Python bindings for the Nominal Rust streaming client
License: MIT
Requires-Python: >=3.10
Project-URL: Source Code, https://github.com/nominal-io/nominal-streaming
